dxc_helmet/__init__.py
dxc_helmet/__main__.py
dxc_helmet/dxc_admin.py
dxc_helmet/pretrained_models.py
dxc_helmet-0.3.4.dist-info/METADATA
dxc_helmet-0.3.4.dist-info/WHEEL
dxc_helmet-0.3.4.dist-info/top_level.txt
dxc_helmet-0.3.4.dist-info/RECORD
