Metadata-Version: 2.1
Name: dxc-helmet
Version: 0.3.4
Summary: Helmet detector
Home-page: UNKNOWN
Author: Jonathan Fernandes
License: MIT
Platform: UNKNOWN
